unsure/__init__.py
unsure/boe.py
unsure/cli.py
unsure-0.3.0.dist-info/LICENSE
unsure-0.3.0.dist-info/WHEEL
unsure-0.3.0.dist-info/METADATA
unsure-0.3.0.dist-info/RECORD
