Metadata-Version: 2.1
Name: unsure
Version: 0.3.0
Summary: 
Author: Vasanth Sarathy
Author-email: vsarathy@sift.net
Requires-Python: >=3.8,<4.0
Classifier: Programming Language :: Python :: 3
Classifier: Programming Language :: Python :: 3.8
Classifier: Programming Language :: Python :: 3.9
Requires-Dist: click (>=8.1.3,<9.0.0)
Requires-Dist: ipykernel (>=6.13.0,<7.0.0)
Requires-Dist: jupyter (>=1.0.0,<2.0.0)
Requires-Dist: pandas (>=1.4.2,<2.0.0)
Requires-Dist: sphinx-rtd-theme (>=1.0.0,<2.0.0)
